README.md
setup.py
draftfast/__init__.py
draftfast/dke_exceptions.py
draftfast/exposure.py
draftfast/lineup_constraints.py
draftfast/optimize.py
draftfast/optimizer.py
draftfast/orm.py
draftfast/player_pool.py
draftfast/rules.py
draftfast/rules_utils.py
draftfast/settings.py
draftfast.egg-info/PKG-INFO
draftfast.egg-info/SOURCES.txt
draftfast.egg-info/dependency_links.txt
draftfast.egg-info/requires.txt
draftfast.egg-info/top_level.txt
draftfast/constants/__init__.py
draftfast/constants/positions.py
draftfast/constants/roster_size.py
draftfast/constants/salary_cap.py
draftfast/csv_parse/__init__.py
draftfast/csv_parse/mlb_upload.py
draftfast/csv_parse/salary_download.py
draftfast/csv_parse/upload.py
draftfast/csv_parse/uploaders.py
draftfast/pickem/__init__.py
draftfast/pickem/pickem_command_line.py
draftfast/pickem/pickem_optimize.py
draftfast/pickem/pickem_orm.py
draftfast/pickem/pickem_upload.py
draftfast/showdown/__init__.py
draftfast/showdown/orm.py
draftfast/test/__init__.py
draftfast/test/test_csgo_showdown.py
draftfast/test/test_csv_parse.py
draftfast/test/test_csv_upload.py
draftfast/test/test_custom.py
draftfast/test/test_custom_rules.py
draftfast/test/test_el.py
draftfast/test/test_exposure.py
draftfast/test/test_f1_showdown.py
draftfast/test/test_golf.py
draftfast/test/test_lineup_constraints.py
draftfast/test/test_mlb.py
draftfast/test/test_nba_general.py
draftfast/test/test_nfl_showdown.py
draftfast/test/test_nhl.py
draftfast/test/test_optimize.py
draftfast/test/test_pickem.py
draftfast/test/test_player.py
draftfast/test/test_player_pool.py
draftfast/test/test_roster.py
draftfast/test/test_ruleset_equality.py
draftfast/test/test_soccer.py
draftfast/test/test_tennis.py
draftfast/test/test_xfl.py
examples/__init__.py
examples/nba.py
examples/pickem.py
examples/showdown.py