Metadata-Version: 2.1
Name: draftfast
Version: 3.12.2
Summary: A tool to automate and optimize DraftKings and FanDuel lineup construction.
Home-page: https://github.com/BenBrostoff/draftfast
Author: Ben Brostoff
Author-email: ben.brostoff@gmail.com
Classifier: Programming Language :: Python :: 3
Classifier: License :: OSI Approved :: MIT License
Classifier: Operating System :: OS Independent
Requires-Dist: numpy==1.26.2
Requires-Dist: terminaltables==3.1.0
Requires-Dist: ortools==9.8.3296
